bobobotLib/__init__.py
bobobotLib/boboBot.py
boboBot-2.4.dist-info/METADATA
boboBot-2.4.dist-info/WHEEL
boboBot-2.4.dist-info/top_level.txt
boboBot-2.4.dist-info/RECORD
